LICENSE.txt
MANIFEST.in
README.rst
setup.py
dlkit/__init__.py
dlkit.egg-info/PKG-INFO
dlkit.egg-info/SOURCES.txt
dlkit.egg-info/dependency_links.txt
dlkit.egg-info/requires.txt
dlkit.egg-info/top_level.txt
dlkit/abstract_osid/__init__.py
dlkit/abstract_osid/assessment/__init__.py
dlkit/abstract_osid/assessment/license.py
dlkit/abstract_osid/assessment/managers.py
dlkit/abstract_osid/assessment/objects.py
dlkit/abstract_osid/assessment/queries.py
dlkit/abstract_osid/assessment/query_inspectors.py
dlkit/abstract_osid/assessment/receivers.py
dlkit/abstract_osid/assessment/record_templates.py
dlkit/abstract_osid/assessment/rules.py
dlkit/abstract_osid/assessment/search_orders.py
dlkit/abstract_osid/assessment/searches.py
dlkit/abstract_osid/assessment/sessions.py
dlkit/abstract_osid/assessment_authoring/__init__.py
dlkit/abstract_osid/assessment_authoring/license.py
dlkit/abstract_osid/assessment_authoring/managers.py
dlkit/abstract_osid/assessment_authoring/objects.py
dlkit/abstract_osid/assessment_authoring/queries.py
dlkit/abstract_osid/assessment_authoring/query_inspectors.py
dlkit/abstract_osid/assessment_authoring/receivers.py
dlkit/abstract_osid/assessment_authoring/record_templates.py
dlkit/abstract_osid/assessment_authoring/search_orders.py
dlkit/abstract_osid/assessment_authoring/searches.py
dlkit/abstract_osid/assessment_authoring/sessions.py
dlkit/abstract_osid/authentication/__init__.py
dlkit/abstract_osid/authentication/license.py
dlkit/abstract_osid/authentication/managers.py
dlkit/abstract_osid/authentication/objects.py
dlkit/abstract_osid/authentication/queries.py
dlkit/abstract_osid/authentication/query_inspectors.py
dlkit/abstract_osid/authentication/receivers.py
dlkit/abstract_osid/authentication/record_templates.py
dlkit/abstract_osid/authentication/search_orders.py
dlkit/abstract_osid/authentication/searches.py
dlkit/abstract_osid/authentication/sessions.py
dlkit/abstract_osid/authentication_process/__init__.py
dlkit/abstract_osid/authentication_process/license.py
dlkit/abstract_osid/authentication_process/managers.py
dlkit/abstract_osid/authentication_process/objects.py
