Metadata-Version: 1.1
Name: dlkit
Version: 0.6.9
Summary: Digital Learning Toolkit
Home-page: https://github.com/mitsei/dlkit
Author: MIT ODL, SEI
Author-email: dlkit@mit.edu
License: MIT
Keywords: education learning assessment
Platform: UNKNOWN
Classifier: Development Status :: 3 - Alpha
Classifier: Intended Audience :: Developers
Classifier: Topic :: Software Development :: Build Tools
Classifier: License :: OSI Approved :: MIT License
Classifier: Programming Language :: Python :: 2
Classifier: Programming Language :: Python :: 2.7
Classifier: Programming Language :: Python :: 3
Classifier: Programming Language :: Python :: 3.4
Classifier: Programming Language :: Python :: 3.5
Classifier: Programming Language :: Python :: 3.6
